README.md
setup.cfg
setup.py
trello_board_reader/__init__.py
trello_board_reader/reader.py
trello_board_reader.egg-info/PKG-INFO
trello_board_reader.egg-info/SOURCES.txt
trello_board_reader.egg-info/dependency_links.txt
trello_board_reader.egg-info/requires.txt
trello_board_reader.egg-info/top_level.txt