Metadata-Version: 1.1
Name: trello-board-reader
Version: 1.1
Summary: Small tool to help read from Trello boards
Home-page: https://github.com/Salil999/TrelloBoardReader
Author: Shashank Saxena
Author-email: saxena.shashank96@gmail.com
License: UNKNOWN
Download-URL: https://github.com/Salil999/TrelloBoardReader/archive/1.0.tar.gz
Keywords: trello,trello-board,scraper
Platform: UNKNOWN
